LICENSE
MANIFEST.in
README.md
setup.cfg
setup.py
dblue_stores/__init__.py
dblue_stores/exceptions.py
dblue_stores/logger.py
dblue_stores/settings.py
dblue_stores/utils.py
dblue_stores.egg-info/PKG-INFO
dblue_stores.egg-info/SOURCES.txt
dblue_stores.egg-info/dependency_links.txt
dblue_stores.egg-info/requires.txt
dblue_stores.egg-info/top_level.txt
dblue_stores/clients/__init__.py
dblue_stores/clients/aws.py
dblue_stores/clients/azure.py
dblue_stores/clients/base.py
dblue_stores/clients/gcp.py
dblue_stores/clients/sftp.py
dblue_stores/stores/__init__.py
dblue_stores/stores/azure.py
dblue_stores/stores/base.py
dblue_stores/stores/gcs.py
dblue_stores/stores/local.py
dblue_stores/stores/manager.py
dblue_stores/stores/s3.py
dblue_stores/stores/sftp.py
tests/__init__.py
tests/clients/__init__.py
tests/clients/test_aws.py
tests/clients/test_azure.py
tests/clients/test_gcp.py
tests/stores/__init__.py
tests/stores/test_azure.py
tests/stores/test_gcs.py
tests/stores/test_s3.py
tests/stores/test_utils.py