Metadata-Version: 2.1
Name: dblue-stores
Version: 2.0.2
Summary: Dblue stores is an abstraction and a collection of clients to interact with storages.
Home-page: https://github.com/dblueai/dblue-stores
Author: Rajesh Hegde
Author-email: rh@dblue.ai
Maintainer: Rajesh Hegde
Maintainer-email: rh@dblue.ai
License: MIT
Keywords: dblue,aws,s3,microsoft,azure,google cloud storage,gcs,machine-learning,data-science,artificial-intelligence,ai,reinforcement-learning,kubernetes,docker,sftp
Platform: any
Classifier: Programming Language :: Python
Classifier: Operating System :: OS Independent
Classifier: Intended Audience :: Developers
Classifier: Intended Audience :: Science/Research
Classifier: Topic :: Scientific/Engineering :: Artificial Intelligence
Provides-Extra: s3
Provides-Extra: gcs
Provides-Extra: azure
Provides-Extra: sftp
